posebusters/__init__.py
posebusters/__main__.py
posebusters/cli.py
posebusters/posebusters.py
posebusters/py.typed
posebusters/config/dock.yml
posebusters/config/dock_fast.yml
posebusters/config/gen.yml
posebusters/config/gen_fast.yml
posebusters/config/mol.yml
posebusters/config/mol_fast.yml
posebusters/config/redock.yml
posebusters/config/redock_fast.yml
posebusters/config/regen.yml
posebusters/config/regen_fast.yml
posebusters/datasets/__init__.py
posebusters/datasets/load_datasets.py
posebusters/datasets/pdb.csv
posebusters/datasets/pdb/1ia1/1ia1_ligand.sdf
posebusters/datasets/pdb/1ia1/1ia1_ligands.sdf
posebusters/datasets/pdb/1ia1/1ia1_protein_one_lig_removed.pdb
posebusters/datasets/pdb/1of6/1of6_ligand.sdf
posebusters/datasets/pdb/1of6/1of6_ligands.sdf
posebusters/datasets/pdb/1of6/1of6_protein_one_lig_removed.pdb
posebusters/datasets/pdb/1s3v/1s3v_ligand.sdf
posebusters/datasets/pdb/1s3v/1s3v_ligands.sdf
posebusters/datasets/pdb/1s3v/1s3v_protein_one_lig_removed.pdb
posebusters/datasets/pdb/1uou/1uou_ligand.sdf
posebusters/datasets/pdb/1uou/1uou_ligands.sdf
posebusters/datasets/pdb/1uou/1uou_protein_one_lig_removed.pdb
posebusters/modules/__init__.py
posebusters/modules/distance_geometry.py
posebusters/modules/energy_ratio.py
posebusters/modules/flatness.py
posebusters/modules/identity.py
posebusters/modules/intermolecular_distance.py
posebusters/modules/loading.py
posebusters/modules/rmsd.py
posebusters/modules/sanity.py
posebusters/modules/sucos.py
posebusters/modules/volume_overlap.py
posebusters/tools/__init__.py
posebusters/tools/formatting.py
posebusters/tools/inchi.py
posebusters/tools/loading.py
posebusters/tools/logging.py
posebusters/tools/molecules.py
posebusters/tools/protein.py
posebusters/tools/stats.py
posebusters-0.6.3.dist-info/entry_points.txt
posebusters-0.6.3.dist-info/licenses/LICENSE
posebusters-0.6.3.dist-info/WHEEL
posebusters-0.6.3.dist-info/METADATA
posebusters-0.6.3.dist-info/RECORD
