Metadata-Version: 2.4
Name: posebusters
Version: 0.6.3
Summary: PoseBusters: Plausibility checks for generated molecule poses.
Keywords: posebusters,docking,tests,metric
Author-email: Martin Buttenschoen <martin.buttenschoen@stats.ox.ac.uk>
Requires-Python: >=3.9
Classifier: Development Status :: 4 - Beta
Classifier: Topic :: Scientific/Engineering :: Bio-Informatics
Classifier: Intended Audience :: Science/Research
Classifier: License :: OSI Approved :: BSD License
Classifier: Programming Language :: Python :: 3 :: Only
Classifier: Programming Language :: Python :: 3.10
Classifier: Programming Language :: Python :: 3.11
Classifier: Programming Language :: Python :: 3.12
Classifier: Programming Language :: Python :: 3.13
Classifier: Programming Language :: Python :: 3.14
Classifier: Operating System :: OS Independent
License-File: LICENSE
Requires-Dist: rdkit >= 2024.9
Requires-Dist: pandas
Requires-Dist: numpy
Requires-Dist: pyyaml
Project-URL: Documentation, https://posebusters.readthedocs.io/en/latest/
Project-URL: Source, https://github.com/maabuu/posebusters/
Project-URL: Tracker, https://github.com/maabuu/posebusters/issues/
